markdown_to_sqlite/__init__.py
markdown_to_sqlite/cli.py
markdown_to_sqlite-1.0.dist-info/LICENSE
markdown_to_sqlite-1.0.dist-info/METADATA
markdown_to_sqlite-1.0.dist-info/WHEEL
markdown_to_sqlite-1.0.dist-info/entry_points.txt
markdown_to_sqlite-1.0.dist-info/top_level.txt
markdown_to_sqlite-1.0.dist-info/RECORD
