Metadata-Version: 2.1
Name: markdown-to-sqlite
Version: 1.0
Summary: CLI tool for loading markdown files into a SQLite database
Home-page: https://github.com/simonw/markdown-to-sqlite
Author: Simon Willison
License: Apache License, Version 2.0
Project-URL: Issues, https://github.com/simonw/markdown-to-sqlite/issues
Project-URL: CI, https://github.com/simonw/markdown-to-sqlite/actions
Project-URL: Changelog, https://github.com/simonw/markdown-to-sqlite/releases
Platform: UNKNOWN
Classifier: Intended Audience :: Developers
Classifier: Intended Audience :: Science/Research
Classifier: Intended Audience :: End Users/Desktop
Classifier: Topic :: Database
Classifier: License :: OSI Approved :: Apache Software License
Classifier: Programming Language :: Python :: 3.6
Classifier: Programming Language :: Python :: 3.7
Requires-Python: >=3.6
Requires-Dist: yamldown
Requires-Dist: markdown
Requires-Dist: sqlite-utils
Requires-Dist: click
Provides-Extra: test
Requires-Dist: pytest ; extra == 'test'
